otio_ale_adapter/__init__.py
otio_ale_adapter/ale.py
otio_ale_adapter/plugin_manifest.json
otio_ale_adapter-1.1.0.dist-info/METADATA
otio_ale_adapter-1.1.0.dist-info/WHEEL
otio_ale_adapter-1.1.0.dist-info/entry_points.txt
otio_ale_adapter-1.1.0.dist-info/licenses/LICENSE
otio_ale_adapter-1.1.0.dist-info/RECORD
