Metadata-Version: 2.4
Name: otio-ale-adapter
Version: 1.1.0
Summary: OpenTimelineIO ALE Adapter
Project-URL: Homepage, https://github.com/OpenTimelineIO/otio-ale-adapter
Project-URL: Tracker, https://github.com/OpenTimelineIO/otio-ale-adapter/issues
Author-email: Contributors to the OpenTimelineIO project <otio-discussion@lists.aswf.io>
License: 
License-File: LICENSE
Keywords: ale,edit,editing,editorial,film,non-linear,otio,otio-adapter,time,tv
Classifier: Development Status :: 5 - Production/Stable
Classifier: License :: OSI Approved :: Apache Software License
Classifier: Natural Language :: English
Classifier: Operating System :: OS Independent
Classifier: Programming Language :: Python :: 3
Classifier: Programming Language :: Python :: 3.7
Classifier: Programming Language :: Python :: 3.8
Classifier: Programming Language :: Python :: 3.9
Classifier: Programming Language :: Python :: 3.10
Classifier: Programming Language :: Python :: 3.11
Classifier: Topic :: Multimedia :: Graphics
Classifier: Topic :: Multimedia :: Video
Classifier: Topic :: Multimedia :: Video :: Display
Classifier: Topic :: Multimedia :: Video :: Non-Linear Editor
Classifier: Topic :: Software Development :: Libraries :: Python Modules
Requires-Python: >=3.9
Requires-Dist: opentimelineio>=0.18.1
